serial_to_parallel.v
module serial_to_parallel (
    input clk,
    input reset,
    input serial_in,
    output reg [7:0] parallel_out
);

always @(posedge clk or posedge reset) begin
    if (reset)
         parallel_out <= 8'b00000000;
    else
        parallel_out <= {parallel_out[6:0], serial_in};
end

endmodule

tb_serial_to_parallel.v
module tb_serial_to_parallel;

reg clk;
reg reset;
reg serial_in;
wire [7:0] parallel_out;

serial_to_parallel uut (
    .clk(clk),
    .reset(reset),
    .serial_in(serial_in),
    .parallel_out(parallel_out)
);


always #5 clk = ~clk;

initial begin
    
    $dumpfile("waves.vcd");
    $dumpvars(0, tb_serial_to_parallel);
    
    
    clk = 0;
    reset = 1;
    serial_in = 0;

    #10 reset = 0;

    
    serial_in = 1; #10;
    serial_in = 0; #10;
    serial_in = 1; #10;
    serial_in = 1; #10;
    serial_in = 0; #10;
    serial_in = 1; #10;
    serial_in = 0; #10;
    serial_in = 1; #10;

    #50 $finish;
end

endmodule

waves.vcd
$date
	Fri May 01 15:46:07 2026
$end
$version
	Icarus Verilog
$end
$timescale
	1s
$end
$scope module tb_serial_to_parallel $end
$var wire 8 ! parallel_out [7:0] $end
$var reg 1 " clk $end
$var reg 1 # reset $end
$var reg 1 $ serial_in $end
$scope module uut $end
$var wire 1 " clk $end
$var wire 1 # reset $end
$var wire 1 $ serial_in $end
$var reg 8 % parallel_out [7:0] $end
$upscope $end
$upscope $end
$enddefinitions $end
$comment Show the parameter values. $end
$dumpall
$end
#0
$dumpvars
b0 %
0$
1#
0"
b0 !
$end
#5
1"
#10
0"
1$
0#
#15
b1 !
b1 %
1"
#20
0"
0$
#25
b10 !
b10 %
1"
#30
0"
1$
#35
b101 !
b101 %
1"
#40
0"
#45
b1011 !
b1011 %
1"
#50
0"
0$
#55
b10110 !
b10110 %
1"
#60
0"
1$
#65
b101101 !
b101101 %
1"
#70
0"
0$
#75
b1011010 !
b1011010 %
1"
#80
0"
1$
#85
b10110101 !
b10110101 %
1"
#90
0"
#95
b1101011 !
b1101011 %
1"
#100
0"
#105
b11010111 !
b11010111 %
1"
#110
0"
#115
b10101111 !
b10101111 %
1"
#120
0"
#125
b1011111 !
b1011111 %
1"
#130
0"
#135
b10111111 !
b10111111 %
1"
